minorun365/__init__.py
minorun365/__main__.py
minorun365/card.py
minorun365-1.0.10.dist-info/METADATA
minorun365-1.0.10.dist-info/WHEEL
minorun365-1.0.10.dist-info/entry_points.txt
minorun365-1.0.10.dist-info/licenses/LICENSE
minorun365-1.0.10.dist-info/RECORD
