Metadata-Version: 2.4
Name: minorun365
Version: 1.0.10
Summary: minorun365のプロフィールを表示するカードパッケージ
Project-URL: Homepage, https://github.com/minorun365/minorun365-card
Project-URL: Bug Tracker, https://github.com/minorun365/minorun365-card/issues
Author: minorun365
License: MIT
License-File: LICENSE
Keywords: card,cli,minorun365,profile
Classifier: Development Status :: 5 - Production/Stable
Classifier: License :: OSI Approved :: MIT License
Classifier: Operating System :: OS Independent
Classifier: Programming Language :: Python :: 3
Classifier: Programming Language :: Python :: 3.7
Classifier: Programming Language :: Python :: 3.8
Classifier: Programming Language :: Python :: 3.9
Classifier: Programming Language :: Python :: 3.10
Classifier: Programming Language :: Python :: 3.11
Classifier: Programming Language :: Python :: 3.12
Requires-Python: >=3.7
Requires-Dist: hatchling>=1.17.1
Requires-Dist: rich>=13.0.0
Requires-Dist: typer>=0.9.0
